[
  {
    "name": "فيلم الدشاش 2025 كامل HD",
    "url": "https://s302d1.downet.net/download/1771200294/69910da6e2cae/El.Dashash.2025.720p.WEB-DL.AKWAM.mp4",
    "img": "https://h.top4top.io/p_3693sy9ma9.jpg",
    "isSeries": false
  },
  {
    "name": "فيلم قصر الباشا 2025 كامل HD",
    "url": "https://s203d1.downet.net/download/1771374758/6993b7262bad8/Qasr.El.Basha.1080p.WEB-DL.AKWAM.mp4",
    "img": "https://e.top4top.io/p_3693yfijd9.jpeg",
    "isSeries": false
  },
  {
    "name": "فيلم المشروع x اكس 2025 كامل HD",
    "url": "https://s302d1.downet.net/download/1771200107/69910ceb867f9/Al.Mashroa.X.720.WEB-DL.AKWAM.mp4",
    "img": "https://i.top4top.io/p_3693jixo99.jpg",
    "isSeries": false
  },
  {
    "name": "فيلم فيها إيه يعني 2025 كامل HD",
    "url": "https://s204d1.downet.net/download/1771374833/6993b77199df1/Feeha Eh Yaani.2025.1080p.WEB-DL.AKWAM.mp4",
    "img": "https://h.top4top.io/p_36931e24l9.jpeg",
    "isSeries": false
  },
  {
    "name": "فيلم روكي الغلابة 2025 كامل HD",
    "url": "https://s302d3.downet.net/download/1771199799/69910bb7d19c9/Rocky.El.Ghalaba.720p.WEB-DL.AKWAM.mp4",
    "img": "https://g.top4top.io/p_3693sc64d9.jpeg",
    "isSeries": false
  },
  {
    "name": "فيلم سعد اليتيم",
    "url": "https://s301d4.downet.net/download/1771200664/69910f187dd78/Saad.Alyateem.1985.480P.WEB-DL.AKWAM.mp4",
    "img": "https://a.top4top.io/p_3697km5wi1.jpg",
    "isSeries": false
  },
  {
    "name": "فيلم البعبع",
    "url": "https://s301d4.downet.net/download/1771201803/6991138b30d48/El.BoBo.2023.720P.HD.AKWAM.mp4",
    "img": "https://j.top4top.io/p_3697uak9x1.jpg",
    "isSeries": false
  },
  {
    "name": "فيلم عنتر بن شداد",
    "url": "https://s302d1.downet.net/download/1771202593/699116a15bf10/Antar.Ibn.Shaddad.1961.480P.WEB-DL.AKWAM.mp4",
    "img": "https://i.top4top.io/p_3697gax8t1.jpg",
    "isSeries": false
  },
  {
    "name": "فيلم كيره و الجن",
    "url": "https://s302d1.downet.net/download/1771203149/699118cd973a3/Kira.Wel.Gen.2022.720P.WEB-DL.AKWAM.mp4",
    "img": "https://l.top4top.io/p_36988l30g1.jpg",
    "isSeries": false
  },
  {
    "name": "فيلم الرعب المصري الكلاسيكي التعويذه",
    "url": "https://s302d2.downet.net/download/1771203350/6991199631321/Altaawitha.1987.720P.WEB-DL.AKWAM.mp4",
    "img": "https://c.top4top.io/p_3697zl4k31.jpg",
    "isSeries": false
  },
  {
    "name": "فيلم الكوميديا بعد الشر",
    "url": "https://s302d2.downet.net/download/1771203805/69911b5df3437/Ba3d.El.Shar.HDCAM.1080p.AKWAM.mp4",
    "img": "https://j.top4top.io/p_3698l8w4k1.jpg",
    "isSeries": false
  },
  {
    "name": "فيلم هيبتا 2: المناظرة الأخيرة",
    "url": "https://s202d1.downet.net/download/1771204519/69911e27c0cc2/Hepta.2.720p.WEB-DL.AKWAM.mp4",
    "img": "https://f.top4top.io/p_36970rqol1.jpeg",
    "isSeries": false
  },
  {
    "name": "فيلم الشاطر",
    "url": "https://s302d2.downet.net/download/1771204930/69911fc22c1ba/El.Shater.720p.WEB-DL.AKWAM.mp4",
    "img": "https://i.top4top.io/p_3697beigw1.jpg",
    "isSeries": false
  },
  {
    "name": "فيلم درويش",
    "url": "https://s302d1.downet.net/download/1771205175/699120b76599f/Darweesh.720p.WEB-DL.AKWAM.mp4",
    "img": "https://i.top4top.io/p_3697gmwcx1.jpg",
    "isSeries": false
  },
  {
    "name": "فيلم البحث عن منفذ لخروج السيد رامبو",
    "url": "https://s302d3.downet.net/download/1771205394/699121927f557/Seeking.Haven.For.Mr.Rambo.720p.WEB-DL.AKWAM.mp4",
    "img": "https://k.top4top.io/p_3697l1rk01.jpg",
    "isSeries": false
  },
  {
    "name": "فيلم لعبة شيطان",
    "url": "https://s302d2.downet.net/download/1771207273/699128e9acf52/Devils.Game.2022.1080P.WEB-DL.AKWAM.mp4",
    "img": "https://h.top4top.io/p_36978bnmz1.jpg",
    "isSeries": false
  },
  {
    "name": "فيلم بيت ست",
    "url": "https://s302d3.downet.net/download/1771210884/69913704ae01c/House.of.setnakht.2019.1080p.WEB-DL.AKWAM.mp4",
    "img": "https://e.top4top.io/p_3698j9jq66.jpeg",
    "isSeries": false
  }
]
